boto_wrapper_doc_pkg/__init__.py
boto_wrapper_doc_pkg/boto_wrapper_doc.py
boto_wrapper_doc_pkg/getenv.py
boto_wrapper_doc_20-0.0.8.dist-info/LICENSE
boto_wrapper_doc_20-0.0.8.dist-info/METADATA
boto_wrapper_doc_20-0.0.8.dist-info/WHEEL
boto_wrapper_doc_20-0.0.8.dist-info/top_level.txt
boto_wrapper_doc_20-0.0.8.dist-info/RECORD
