Metadata-Version: 2.1
Name: boto-wrapper-doc-20
Version: 0.0.8
Summary: Simple wrapper over boto3 client for S3, Cognito and SNS clients
Home-page: https://github.com/rdarshane/boto-wrapper-doc
Author: Rushikesh Darshane
Author-email: x20231580@student.ncirl.ie
License: UNKNOWN
Platform: UNKNOWN
Classifier: Programming Language :: Python :: 3
Classifier: License :: OSI Approved :: MIT License
Classifier: Operating System :: OS Independent
Requires-Python: >=3.6
License-File: LICENSE
Requires-Dist: boto3
